bio2bel_pfam/__init__.py
bio2bel_pfam/__main__.py
bio2bel_pfam/cli.py
bio2bel_pfam/constants.py
bio2bel_pfam/manager.py
bio2bel_pfam/models.py
bio2bel_pfam/parsers.py
bio2bel_pfam-0.0.1.dist-info/LICENSE
bio2bel_pfam-0.0.1.dist-info/METADATA
bio2bel_pfam-0.0.1.dist-info/WHEEL
bio2bel_pfam-0.0.1.dist-info/entry_points.txt
bio2bel_pfam-0.0.1.dist-info/top_level.txt
bio2bel_pfam-0.0.1.dist-info/RECORD
