Metadata-Version: 2.1
Name: bio2bel-pfam
Version: 0.0.1
Summary: Bio2BEL PFAM.
Home-page: https://github.com/bio2bel/pfam
Author: Charles Tapley Hoyt
Author-email: charles.hoyt@scai.fraunhofer.de
Maintainer: Charles Tapley Hoyt
Maintainer-email: charles.hoyt@scai.fraunhofer.de
License: MIT
Keywords: Biological Expression Language,Bio2BEL
Platform: UNKNOWN
Classifier: Development Status :: 1 - Planning
Classifier: Intended Audience :: Developers
Classifier: Programming Language :: Python
Classifier: Programming Language :: Python :: 3.7
Classifier: Programming Language :: Python :: 3.6
Classifier: Programming Language :: Python :: 3 :: Only
Classifier: License :: OSI Approved :: MIT License
Requires-Python: >=3.6
Requires-Dist: bio2bel
Requires-Dist: pybel
Requires-Dist: sqlalchemy
Requires-Dist: tqdm
